bili23/__init__.py
bili23/bili23.py
bili23/cli/__init__.py
bili23/cli/common.py
bili23/cli/download.py
bili23/utils/__init__.py
bili23/utils/api.py
bili23/utils/audio.py
bili23/utils/bangumi.py
bili23/utils/config.conf
bili23/utils/config.py
bili23/utils/download.py
bili23/utils/live.py
bili23/utils/tools.py
bili23/utils/video.py
bili23-1.1.1.dist-info/LICENSE
bili23-1.1.1.dist-info/METADATA
bili23-1.1.1.dist-info/WHEEL
bili23-1.1.1.dist-info/entry_points.txt
bili23-1.1.1.dist-info/top_level.txt
bili23-1.1.1.dist-info/RECORD
